ubigeos/__init__.py
ubigeos/apps.py
ubigeos/models.py
ubigeos/serializers.py
ubigeos/tests.py
ubigeos/urls.py
ubigeos/views.py
ubigeos/fixtures/ubigeos.json
ubigeos/migrations/0001_initial.py
ubigeos/migrations/0002_auto_20210325_1040.py
ubigeos/migrations/__init__.py
django_ubigeo_peru-0.5.0.dist-info/AUTHORS
django_ubigeo_peru-0.5.0.dist-info/LICENSE
django_ubigeo_peru-0.5.0.dist-info/METADATA
django_ubigeo_peru-0.5.0.dist-info/WHEEL
django_ubigeo_peru-0.5.0.dist-info/top_level.txt
django_ubigeo_peru-0.5.0.dist-info/RECORD
