Metadata-Version: 2.1
Name: django-ubigeo-peru
Version: 0.5.0
Summary: Django app for applications that require to use the ubigeos of INEI of Peru.
Home-page: https://gitlab.com/miguelcumpa/django-ubigeo-peru
Download-URL: https://pypi.org/project/django-ubigeo-peru/
Author: Miguel Ángel Cumpa Ascuña
Author-email: miguel.cumpa@yandex.com
License: BSD
Keywords: ubigeos,peru
Classifier: Development Status :: 4 - Beta
Classifier: Framework :: Django
Classifier: Intended Audience :: Developers
Classifier: Operating System :: OS Independent
Classifier: Programming Language :: Python
Classifier: Topic :: Internet :: WWW/HTTP
License-File: LICENSE
License-File: AUTHORS
Requires-Dist: django
Requires-Dist: djangorestframework
Requires-Dist: django-filter
